{"not": 7169, "you": 5671, "have": 4513, "no": 3134, "one": 3065, "like": 1968, "out": 1809, "more": 1793, "up": 1639, "man": 1581, "now": 1411, "only": 1369, "must": 1362, "should": 1257, "those": 1227, "good": 1227, "little": 1224, "great": 1200, "every": 1143, "did": 1141, "see": 1133, "first": 1124, "after": 1118, "men": 1107, "said,": 1082, "these": 1071, "own": 1070, "how": 1068, "over": 1067, "where": 1053, "nor": 1031, "upon": 1029, "make": 1029, "thy": 1025, "time": 1025, "much": 1014, "never": 1000, "made": 1000, "old": 999, "two": 988}